bluewolf/__init__.py
bluewolf/bluewolf.py
bluewolf/command_line.py
bluewolf/proximity.py
bluewolf-0.0.7.3.dist-info/METADATA
bluewolf-0.0.7.3.dist-info/WHEEL
bluewolf-0.0.7.3.dist-info/entry_points.txt
bluewolf-0.0.7.3.dist-info/top_level.txt
bluewolf-0.0.7.3.dist-info/RECORD
