Metadata-Version: 2.1
Name: bluewolf
Version: 0.0.7.3
Summary: Bluetooth Device Tracker
Home-page: http://github.com/wamacdonald89/bluewolf.git
Author: UNKNOWN
Author-email: UNKNOWN
License: UNKNOWN
Platform: UNKNOWN
Requires-Dist: PyBluez
Requires-Dist: PyRIC
Requires-Dist: prettytable
